bk_tree/__init__.py
bk_tree/bktree.py
bk_tree_modification-0.1.2.dist-info/METADATA
bk_tree_modification-0.1.2.dist-info/WHEEL
bk_tree_modification-0.1.2.dist-info/top_level.txt
bk_tree_modification-0.1.2.dist-info/RECORD
