Metadata-Version: 2.1
Name: bk-tree-modification
Version: 0.1.2
Summary: A simple BK-Tree implementation for finding similar words
Home-page: UNKNOWN
Author: Karen Arcoverde
Author-email: arcoverdek@gmail.com
License: UNKNOWN
Keywords: bktree edit distance similarity
Platform: UNKNOWN
Classifier: Development Status :: 3 - Alpha
Classifier: Intended Audience :: Developers
Classifier: Topic :: Software Development :: Libraries
Classifier: License :: OSI Approved :: MIT License
Classifier: Programming Language :: Python :: 3
Classifier: Programming Language :: Python :: 3.7
Classifier: Programming Language :: Python :: 3.8
Classifier: Programming Language :: Python :: 3.9
